smarthyesDash/configFilesSmarthyes.py
smarthyesDash/smarthyesTabs.py
smarthyesDash/confFiles/SmartHyES-10001-001-configurationPLC.csv
smarthyesDash/confFiles/logVersionSmarthyes.md
smarthyesDash/confFiles/predefinedCategories.csv
smarthyesDash-1.6.3.dist-info/METADATA
smarthyesDash-1.6.3.dist-info/WHEEL
smarthyesDash-1.6.3.dist-info/top_level.txt
smarthyesDash-1.6.3.dist-info/RECORD
